{
  "common": {
    "account-levels": {
      "free": "Zastonj",
      "patreon-demon": "Demonski nivo",
      "patreon-minion": "Nivo podložnika",
      "patreon-townsfolk": "Meščanski nivo",
      "special-free": "Darilni",
      "special-moderator": "Moderator",
      "special-tpi": "Zaposleni na TPI"
    },
    "botc_online": "KnZ na spletu",
    "button_cancel": "Prekini",
    "button_close": "Zapri",
    "button_confirm": "Potrdi",
    "button_continue": "Nadaljuj",
    "button_logout": "Izpiši se",
    "button_search": "Išči",
    "button_send": "Pošlji",
    "cookie_policy": "Politika piškotkov",
    "privacy_policy": "Politika zasebnosti",
    "session-tags": {
      "cameras": {
        "label": "Videokamere",
        "title": "Ali so videokamere v uporabi v tej igri",
        "value_0": "Neobvezno",
        "value_1": "Obvezno",
        "value_2": "Ugasnjena"
      },
      "difficulty": {
        "label": "Zahtevnost",
        "title": "Pričakovan nivo izkušenj, ki jih imajo igralci v tej igri",
        "value_0": "Povprečno izkušen",
        "value_1": "Zelo izkušen",
        "value_2": "Začetnik"
      },
      "grimoire": {
        "label": "Dostop do Čarovniške Knjige",
        "title": "Ali opazovalci dobijo dostop do Čarovniške Knjige",
        "value_0": "Na zahtevo",
        "value_1": "Ne",
        "value_2": "Da"
      },
      "streaming": {
        "label": "Se igra pretočno predvaja",
        "title": "Igra bo pretočno predvajana v živo",
        "value_0": "Ne",
        "value_1": "Da"
      },
      "subscription": {
        "label": "Ali je potrebna naročnina",
        "title": "Da se pridružiš tej igri potrebuješ aktivno naročnino"
      },
      "travellers": {
        "label": "Popotniki",
        "title": "Ali so Popotniki dovoljeni v tej igri",
        "value_0": "Lahko",
        "value_1": "Da",
        "value_2": "Ne"
      }
    },
    "terms_of_use": "Pogoji uporabe",
    "title": "\"Kri na zvoniku\" na spletu",
    "trademark": "\"Kri na zvoniku\" je blagovna znamka Steven Medwaya in The Pandemonium Institute.",
    "unnamed_user": "Neimenovan uporabnik"
  },
  "grimoire": {
    "abilities": {
      "distribute-roles": "Razdeli vloge",
      "ghost-votes": "Vrni zadnje glasove mrtvim",
      "grimoire": "Pokaži Čarovniško Knjigo",
      "open-eyes": "Odpri/Zapri oči",
      "pointing": "Izberi igralca"
    },
    "demon": "Demon|Demoni",
    "fabled": "Pravljičen|Pravljični",
    "loric": "Loric|Loric",
    "minion": "Podložnik|Podložniki",
    "outsider": "Tujec|Tujci",
    "phases": {
      "day": "Prvi dan|Dan {n}",
      "end": "Med igrami",
      "first_night": "Prva noč",
      "night": "Prva noč|Noč {n}",
      "other_nights": "Druge noči",
      "start": "Priprave na prvo noč"
    },
    "player": "Igralec {0}",
    "players": "Igralci",
    "seat": "Sedež {0}",
    "shroud": "Mrtvaški prt",
    "storyteller": "Pripovedovalec_ka {0}",
    "storytellers": "Pripovedovalci",
    "token": "Žeton",
    "townsfolk": "Meščan|Meščani",
    "traveller": "Popotnik|Popotniki"
  },
  "main-menu": {
    "cast_vote": "Glasuj",
    "change_icon": "Klikni da spremeniš sliko",
    "char_sheet": "Seznam likov",
    "characters": "Izberi like",
    "clear_grim": "Počisti Čarovniško knjigo",
    "download": "Prenesi {0} aplikacijo",
    "edition": "Izberi izdajo",
    "error_audio": "Tvoj brskalnik je aplikaciji preprečil {0}. Prosim klikni tukaj da začneš pogovor.",
    "error_audio2": "Samodejno predvajanje glasovnega klepeta",
    "error_audio3": "Morda moraš tudi {0} v Firefoxu, da slišiš zvok iz aplikacije.",
    "error_audio4": "Spremeni nastavitev",
    "fullscreen": "Cel zaslon",
    "gather": "Zberi igralce",
    "gong_attention": "Zvon za pozornost",
    "gong_recall": "Pokliči nazaj na mestni trg",
    "grim_access": "Dobil si dostop do Čarovniške Knjige",
    "help": "Pomoč",
    "json_schema": "Shema JSON za skripto",
    "leave": "Zapusti igro",
    "mute_cam": "Ugasni kamero [{0}]",
    "mute_mic": "Ugasni mikrofon [{0}]",
    "night_info": "Nočne informacije",
    "night_info_text": "Pripovedovalec te je zbudil!",
    "night_sheet": "Seznam za nočni red",
    "npcs": "Dodaj NPC-je",
    "prompt_clear_player": "Ste prepričani, da želite odstraniti vse like igralcev in opomnike?",
    "prompt_clear_st": "To bo počistilo celo Čarovniško Knjigo in vse opomnike za vas in vse ostale. Ste prepričani?",
    "prompt_clear_title": "Počisti Čarovniško Knjigo in opomnike",
    "prompt_timer_text": "Izberi trajanje in (neobvezno) naslov za časovnik:",
    "prompt_timer_title": "Nastavi časovnik",
    "prompt_vacate_text": "Trenutno si v igri, ki še poteka. Si prepričan, da želiš zapustiti svoj sedež?",
    "prompt_vacate_title": "Zapusti sedež",
    "push_to_talk": "Pritisni [{0}] da lahko govoriš",
    "raise_hand": "Dvigni roko",
    "request_private": "Zaprosi za zasebni pogovor",
    "reveal_grim": "Razkrij Čarovniško Knjigo",
    "rules": "Preberi pravila",
    "session_expires": "Trenutno v seji ni uporabnika z nivojem Podložnika, tako da se igra lahko zaključi ob {0}.",
    "set_timer": "Nastavi časovnik",
    "settings": "Nastavitve",
    "show_grim": "Prikaži Čarovniško Knjigo",
    "show_town": "Pokaži Mestni trg",
    "show_users": "Prikaži uporabnike [{0}]",
    "storyteller_add": "Postani Pripovedovalec",
    "storyteller_remove": "Prenehaj biti Pripovedovalec",
    "tab_app": "Aplikacija",
    "tab_during_game": "Med igro",
    "tab_new_game": "Nova igra",
    "tab_playing": "Med igro",
    "to_day": "Preidi v dnevno fazo",
    "to_night": "Preidi v nočno fazo",
    "translation": "Izboljšaj ta prevod",
    "user_list": "Seznam uporabnikov",
    "vacate_seat": "Zapusti sedež",
    "vote_history": "Zgodovina glasovanja"
  },
  "modals": {
    "announcement": {
      "description": "Kaj želiš razglasiti?",
      "error": "Napaka pri pošiljanju obvestila",
      "input_session": "Ime seje iger (neobvezno)",
      "input_text": "Tekst tvojega obvestila",
      "input_title": "Naslov obvestila",
      "title": "Naredi obvestilo"
    },
    "dialogue": {
      "button_evil": "Zmagala je zlobna ekipa",
      "button_good": "Zmagala je dobra ekipa",
      "button_no": "Ne",
      "button_yes": "Da",
      "close_timer": "To okno se bo samo zaprlo čez {n} sekund.",
      "error": {
        "add_player": "Ne moremo dodati igralca",
        "add_storyteller": "Napaka pri dodajanju Pripovedovalca",
        "avatar": "Napaka pri nalaganju avatarja",
        "avatar_generic": "Nekaj je šlo narobe pri nalaganju tvojega avatarja.",
        "avatar_pixel": "Tvoja slika je prevelika. Prosim pomanjšaj jo na manj kot 4000x40000 preden jo ponovno naložiš.",
        "avatar_size": "Tvoja datoteka je prevelika. Prosim poskusi ponovno s sliko manjšo od 5 MB.",
        "avatar_type": "Tvoje datoteke nismo prepoznali kot slike.",
        "bluffs": "Napaka pri nalaganju blefov",
        "chat2_text": "Izgleda, da strežnik za klepet ne deluje",
        "chat2_title": "Strežnik za klepet Izklopljen",
        "chat_text": "Izgubili smo povezavo do serverja, poskušamo se povezati ponovno...\nNapaka:{0}",
        "chat_title": "Zgodila se je napaka pri povezavi v pogovor",
        "claiming": "Napaka pri zasedanju sedeža",
        "clear_grim": "Ne moremo počistiti Čarovniške Knjige",
        "connection": "Zgodila se je napaka pri povezavi",
        "create_generic": "Strežnik ni mogel ustvariti vaše seje.",
        "create_rate_limit": "Preden lahko ustvarite novo sejo, morate počakati nekaj minut.",
        "create_session_exists": "Seja s tem imenom že obstaja.",
        "edition_change": "Napaka pri menjavi izdaje",
        "end": "Napaka pri končanju igre",
        "eyes_close": "Ne moremo zapreti oči",
        "eyes_open": "Ne moremo odpreti oči",
        "generic": "Zgodila se je napaka",
        "kick": "Ni mogoče odstraniti uporabnika",
        "link_text": "Napaka pri povezovanju tvojega računa s Patreonom. Prosim, poskusi ponovno.",
        "link_title": "Napaka pri povezovanju računa s Patreonom",
        "loading_text": "Nekaj je šlo narobe pri nalaganju podatkov aplikacije. Stran se bo ponovno naložila.",
        "loading_title": "Napaka pri nalaganju podatkov aplikacije",
        "missing_edition": "Ta seja vsebuje izdajo, ki je ne moremo najti.",
        "missing_edition_title": "Napaka pri nalaganju izdaje",
        "missing_roles": "Ta seja vključuje izvenserijske like, ki jih ne moremo najti. Prosim naložite jih, preden se pridtužite! Manjkajoče vloge: {0}",
        "missing_roles_title": "Napaka pri nalaganju izvenserijskih vlog",
        "move_player": "Ne moremo premakniti igralca",
        "npcs": "Napaka pri posodabljanju NPC-jev",
        "offline": "Izgleda, da strežnik ni povezan",
        "remove_player": "Ne moremo odstraniti igralca",
        "remove_storyteller": "Napaka pri odstranjanju Pripovedovalca",
        "request_grim": "Ne moremo zaprositi za dostop do Čarovniške Knjige",
        "running": "Napaka pri spreminjanju trenutnega stanja",
        "sending_roles": "Napaka pri pošiljanju vlog",
        "server2_text": "Izgubljena povezava s serverjem, poskušamo se povezati ponovno...\n Sporočilo napake: {0}",
        "server_change": "Ne moremo spremeniti pogovornega serverja",
        "server_text": "Povezava je potekla med čakanjem na strežnik za igro.",
        "server_title": "Strežnik za igro izklopljen",
        "session": "Napaka pri odpiranju seje igre",
        "session_banned": "Imaš prepoved.",
        "session_full": "Ta seja že ima 25 uporabnikov.",
        "session_general": "Napaka pri povezovanju s sejo.",
        "session_locked": "Seja igre je zaklenjena.\n Pridružijo se lahko samo igralci, ki že sedijo in Pripovedovalci.",
        "session_not_found": "Nismo našli seje igre.",
        "session_public": "Ne moreš se pridružiti javnim sejam iger.",
        "session_rejoin": "Ne moreš se še ponovno pridružiti tej seji.",
        "session_subscription": "Da se pridružiš tej igri, potrebuješ naročnino.",
        "session_unverified": "Svoj račun moraš potrditi, preden se lahko pridružiš javnim igram.",
        "signal": "Napaka pri pošiljanju nočnega sporočila",
        "start": "Napaka pri začetku igre",
        "subscription": "Potrebna je naročnina",
        "subscription_text": "Da se pridružiš tej igri, potrebuješ naročnino.",
        "subscription_title": "Nismo našli Patreon naročnine",
        "theme_change": "Napaka pri spreminjanju teme",
        "unauthorized": "Neavtoriziran",
        "update": "Napaka pri posodabljanju igre",
        "update_game": "Ne moremo posodobiti podatkov seje",
        "update_player": "Ne moremo posodobiti igralca",
        "update_storyteller": "Ne moremo posodobiti Pripovedovalca",
        "user_not_found": "Nismo našli uporabnika.",
        "user_text": "Nekaj je šlo narobe: {0}",
        "user_title": "Napaka pri posodabljanju uporabnika",
        "vacating": "Napaka pri zapuščanju sedeža",
        "video_text": "Tvoj brskalnik je aplikaciji preprečil da bi avtomatsko začela video pogovor, prosim zapri to sporočilo, da se pogovor začne.",
        "video_title": "Napaka pri začetku video pogovora"
      },
      "prompt": {
        "chat_text": "Aplikacija ima probleme doseči server {0}, bi raje preklopil na {1}?",
        "chat_title": "Preklopi server",
        "join_placeholder": "Številka seje",
        "join_text": "Prosim vpiši številko ali ime seje igre, ki bi se ji rad pridružil",
        "join_title": "Pridruži se igri",
        "leave_text": "Si prepričan, da želiš zapustiti trenutno igro in se vrniti v vežo?",
        "leave_text_player": "Si prepričan, da želiš zapustiti sedež in se vrniti v vežo?",
        "leave_title": "Vrni se v vežo",
        "pronouns_placeholder": "Zaimki",
        "pronouns_text": "Prosim vpiši zaimke, ki jih uporabljaš:",
        "pronouns_title": "Vpiši svoje zaimke",
        "storyteller_text": "Ali želiš postati Pripovedovalec in videti Čarovniško Knjigo?",
        "storyteller_title": "Prošnja za povišanje v Pripovedovalca",
        "terms": "Posodobljeni pogoji uporabe",
        "username_placeholder": "Uporabniško ime",
        "username_text": "Prosim, vpiši svoje uporabniško ime:",
        "username_title": "Vpiši svoje uporabniško ime"
      },
      "terms": "S tem, ko uporabljaš spletno verzijo Krvi na zvoniku, potrjuješ da si prebral in se strinjaš s sledečimi pogoji:",
      "terms_confirm": "Potrjujem, da sem prebral in se strinjam s temi pogoji.",
      "timer_paused": "Ustavljeno med nominacijami in glasovanjem",
      "timer_start": "Začni",
      "timer_title": "Naslov časovnika (neobvezno)",
      "unit_minutes": "Minute",
      "unit_seconds": "Sekunde"
    },
    "edition": {
      "button_clear": "Počisti Čarovniško Knjigo",
      "button_paste": "Prilepi",
      "button_upload": "Naloži",
      "button_url": "Povezava",
      "clear_description": "To bo počistilo Čarovniško Knjigo in vse opomnike zate in za vse ostale. Si prepričan?",
      "clear_title": "Počisti Čarovniško Knjigo in opomnike",
      "custom_placeholder": "Povezava do skripte po meri",
      "custom_text": "Vpiši povezavo do custom-script.json datoteke",
      "custom_title": "Naloži Skripto po meri",
      "difficulty": "Težavnost:",
      "difficulty_beginner": "Začetnik",
      "difficulty_intermediate": "Srednji",
      "difficulty_various": "Različni",
      "error_character": "Preveč likov",
      "error_character_text": "Ta skripta vsebuje več kot 200 likov - prosim, odstrani jih nekaj.",
      "error_custom": "Napaka pri nalaganju skripte po meri",
      "error_loading": "Nekaj likov ni bilo naloženih: {0}",
      "error_script": "Skripta ni sprejemljiva",
      "error_script_text": "Skripto smo naložili, ampak ima nekaj težav. To običajno pomeni, da je nekaj vrstic, ki ne bi smele biti tam, glede na uradno JSON shemo lastnih skript.",
      "error_size": "Velikost datoteke je prevelika",
      "error_size_text": "Skripta, ki je izbrana, je velika {0}MB, največja velikost pa je {1}MB.",
      "homebrew_description": "Lastne slike za skripte z doma narejenimi liki, smo iz varnostnih razlogov zamenjali z generičnimi slikami. Svoje slike lahko potrdite v meniju z nastavitvami.",
      "homebrew_title": "Slike po meri niso na voljo",
      "theme": "Tema:",
      "theme_generic": "Splošna tema:",
      "title": "Izberi izdajo:",
      "upload_custom": "Naloži JSON Skripte po meri"
    },
    "help": {
      "button_send": "Pošlji podatke o odpravljanju napak seje",
      "button_stop": "Ustavi pošiljanje podatkov o odpravljanju napak",
      "link_0": "sledilec napak",
      "link_1": "preko e-sporočil",
      "link_2": "tukaj",
      "link_3": "naša spletna trgovina",
      "session_debug": "Prihaja do napak? Lahko pošlješ informacije o tvoji seji in nedavni zgodovini na naš iskalec napak, kar nam bo pomagalo prepoznati težave s katerimi se srečuješ:",
      "session_debug2": "Sledimo tvoji seji na aplikaciji in nam bo samodejno poslana. Sledenje lahko vedno ročno ustaviš tako, da klikneš spodnji gumb ali ponovno naložiš aplikacijo.",
      "text1": "Ta aplikacija (verzija {version}) je trenutno V Delu.",
      "text2": "Povratne informacije lahko pošlješ preko {0} strani ali {1}. Lahko posodobiš svoj e-poštni naslov in geslo svojega uporabniškega računa {2}. Če želiš kupiti igro v fizični obliki, poglej {3}.",
      "welcome": "Dobrodošli na {0}!"
    },
    "npc": {
      "title": "Dodaj neigralski lik"
    },
    "reminder": {
      "custom_favorite": "Shrani kot priljubljeno",
      "custom_note": "Beležka po meri",
      "custom_text": "Dodaj lasten opomnik, ki ga dodaš {0}",
      "custom_title": "Dodaj lasten opomnik",
      "tab1": "Aktualni opomniki",
      "tab2": "Ostali opomniki",
      "title": "Dodaj žetone za opomnike k {0}"
    },
    "role": {
      "error_character": "Nismo našli lika, ki bi ustrezal {0}.",
      "error_traveller": "Nismo našli Popotnika, ki bi ustrezal {0}.",
      "tab_character": "Liki, ki so na voljo",
      "tab_traveller": "Ostali Popotniki",
      "title": "Izberi {alignment} {type} {target}",
      "title_alignment_e": "Zlo",
      "title_alignment_g": "Dober",
      "title_alignment_r": "Navaden",
      "title_target": "za {0}",
      "title_type_bluff": "blef",
      "title_type_character": "lik"
    },
    "roles": {
      "button_distribute": "Razdeli {0} likov",
      "button_gardener": "Določi {0} likov",
      "button_shuffle": "Premešaj",
      "button_sort": "Razdeli",
      "clear": "Pobriši izbrane like",
      "title": "Izberi lik za {0}",
      "title_players": "igralci",
      "warning": "Pozor: izbrani so liki, ki vplivajo na postavitev igre! Za te spremembe moraš poskrbeti ti."
    },
    "rules": {
      "title": "Pravila"
    },
    "settings": {
      "background_placeholder": "URL za ozadje",
      "background_text": "Prosim vstavi URL za lastno ozadje, ali pusti prazno, da odstraniš izbrano ozadje.",
      "background_title": "Lastno ozadje",
      "button_always": "Vedno",
      "button_edit": "Uredi račun",
      "button_setup": "Izpelji postavitev",
      "button_verify": "Potrdi račun",
      "css_apply": "Uporabi CSS Pravila po meri?",
      "css_confirm": "Vem kaj počnem, dovoli mi spremeniti izgled moje aplikacije",
      "css_confirm2": "Prosim potrdi, da želiš obdržati lastne CSS spremembe, drugače jih bomo avtomatsko zavrnili.",
      "css_text": "Tukaj lahko spremeniš videz svoje aplikacije tako, da vstaviš povezavo do lastne CSS datoteke ali vpišeš samo CSS kodo. Pandemonium Institut ni odgovoren za CSS kodo, ki jo spišejo drugi uporabniki. Če naložiš škodljivo CSS kodo, si lahko pokvariš aplikacijo!",
      "css_title": "Naloži lasten CSS",
      "image_text": "Ste prepričani, da želite dovoliti slike po meri? Avtor zlonamerne datoteke lahko tako sledi tvojemu IP naslovu. Pandemonium Institute nima nadzora nad slikami, ki jih nalagajo drugi uporabniki aplikacije.",
      "image_title": "Dovoli slike po meri",
      "nomination": {
        "bigwig": {
          "text": "Vsak nominiranec izbere igralca: do glasovanja lahko govori samo on in je nor, da je nominiranec dober, drugače lahko umre.",
          "title": "Pomembnež"
        },
        "focus": {
          "text": "Nominirani igralec ima pozornost skupine.",
          "title": "Fokus na nominiranem"
        },
        "phases": {
          "text": "Govorita lahko samo nominiranec in nominajoči.",
          "title": "Obtožba in zagovor"
        },
        "regular": {
          "text": "Kdorkoli lahko govori, kakor želi.",
          "title": "Normalno"
        }
      },
      "option_disabled": "Onemogočeno",
      "patreon_link": "Poveži Patreon račun",
      "patreon_perks": "Nalaganje avatarja in posebne ploščice z imeni so na voljo s plačano/-im {0}!",
      "patreon_perks2": "Patreon naročnina",
      "patreon_update": "Posodobi Patreon stanje",
      "setting_alignment": "Pokaži Razvrstitev na Mestnem trgu",
      "setting_animations": "Pokaži Animacije",
      "setting_audio_deafen": "Poslušaj glasovni klepet",
      "setting_audio_unnamed": "Neimenovan zvočni vhod",
      "setting_auto_gain": "Samodejno uravnavanje glasnosti",
      "setting_avatar_size": "Velikost igralčevega avatarja",
      "setting_avatars": "Pokaži avatarje / Kamere na Mestnem trgu",
      "setting_background": "Slika ozadja",
      "setting_camera": "Kamera",
      "setting_chroma": "Kromatsko izrezovanje",
      "setting_chroma_label": "Izberi kromatsko izrezovanje",
      "setting_clouds": "Pokaži oblake v Nočni fazi",
      "setting_colorblind": "Način za barvno slepe: {0}",
      "setting_condense": "Skrči seznam likov",
      "setting_cosmetics": "Pokaži izgled igralca",
      "setting_css": "CSS pravila po meri",
      "setting_css_label": "Vnesi CSS pravila po meri",
      "setting_echo_cancellation": "Zmanjševanje odmeva",
      "setting_english": "Pokaži dodatna imena likov v angleščini",
      "setting_gain": "Avdio glasnost",
      "setting_general_volume": "Splošna glasnost",
      "setting_grimoire_offset": "Odmik Čarovniške Knjige",
      "setting_homebrew": "Pokaži Slike po meri / Doma zvarjene ikone",
      "setting_microphone": "Mikrofon",
      "setting_mute_audio": "Izklop zvoka",
      "setting_mute_video": "Skrij video",
      "setting_noise_suppression": "Zmanjšanje hrupa",
      "setting_player_bluffs": "Igralec: Pokaži zavihek z Liki za pretvarjanje",
      "setting_player_night": "Igralec: Pokaži seznam z Nočnim redom",
      "setting_player_reminders": "Igralec: Dovoli podvojene žetone z opomniki",
      "setting_player_sound": "Igralec: Predvajaj zvočni efekt za prošnjo za klepet ponoči",
      "setting_positioning": "Dovoli premikanje stranskih zavihkov",
      "setting_private_cams": "Pokaži kamere igralcev v zasebnih klepetih",
      "setting_ptt": "Pritisni za govor",
      "setting_reminder_zoom": "Velikost Žetona za opomnik",
      "setting_reminders": "Zloži Žetone za opomnik",
      "setting_reminders_always": "Vedno",
      "setting_reminders_auto": "Samodejno",
      "setting_reminders_never": "Nikoli",
      "setting_reveal": "Pokaži kamere med prikazovanjem Čarovniške Knjige",
      "setting_st_night": "Pripovedovalec: Pokaži Red zbujanja",
      "setting_st_nomination": "Pripovedovalec: Tip nominacije",
      "setting_st_vote": "Pripovedovalec: Čas za Glasovanje",
      "setting_st_whisper": "Pripovedovalec: Dovoli Šepetanje preko sporočil",
      "setting_tutorial": "Pokaži Korake navodil za aplikacijo",
      "setting_video_deafen": "Pokaži Kamere v živo",
      "setting_video_hidden": "Skrij svojo kamero",
      "setting_video_mirrored": "Zrcali svojo kamero",
      "setting_video_unnamed": "Neimenovan video vhod",
      "setting_volume": "Glasnost zvočnih efektov",
      "setting_zoom": "Velikost igralskih žetonov",
      "setup": "Problemi z mikrofonom ali kamero?",
      "shortcut_add": "Dodaj Gumb",
      "shortcut_escape": "Pritisni \"Escape\" za ponastavitev bližnjice",
      "shortcut_record": "Pritisni tipko, ki jo želiš uporabiti za {0}",
      "shortcut_reset": "Ponastavi vse bližnjice",
      "shortcut_reset_confirm": "Želiš ponastaviti vse bližnjice? Tega se ne da razveljaviti.",
      "shortcut_touch": "Podpora za dotik (poteg, itd.)",
      "shortcut_touch_text": "Podpora za geste z dotikom kot so poteg gor / dol",
      "shortcuts": {
        "acceptChat1": "Sprejmi prošnjo za klepet 1",
        "acceptChat2": "Sprejmi prošnjo za klepet 2",
        "acceptChat3": "Sprejmi prošnjo za klepet 3",
        "attentionGong": "Priklic / Gong za pozornost",
        "castVote": "Oddaj glas / Označi igralca",
        "leaveChat": "Odidi iz klepeta",
        "leaveSession": "Odidi iz srečanja",
        "modalRules": "Preberi pravila",
        "modalSettings": "Nastavitve",
        "modalShortcuts": "Bližnjice",
        "modalUsers": "Uporabniki",
        "modeGather": "Zberi svoje igralce",
        "raiseHand": "Dvigni roko",
        "revealGrimoire": "Prikaži Čarovniško Knjigo",
        "setTimer": "Nastavi odštevalnik",
        "toggleAudioDeafened": "Izklopi zvok glasovnega klepeta",
        "toggleAudioMuted": "Ugasni mikrofon / Pritisni za govor",
        "toggleEdition": "Izberi izdajo",
        "toggleFullscreen": "Cel zaslon",
        "toggleNPCs": "Dodaj neigralski lik",
        "toggleNight": "Preklopi Nočno fazo",
        "toggleNightOrder": "Nočni red",
        "toggleNightSignal": "Pokaži Nočne Informacije",
        "toggleReference": "Referenca likov",
        "toggleRoles": "Izberi like",
        "toggleTownSquare": "Pokaži Mestni trg",
        "toggleVideoMuted": "Preklopi kamero",
        "toggleVoteHistory": "Zgodovina glasovanja",
        "toggleWhisper": "Klepet / Sporočilo"
      },
      "sounds": {
        "attentionGong": "Zvon za pozornost",
        "chatJoin": "Vstop v javni klepet",
        "chatLeave": "Izstop iz javnega klepeta",
        "countdown": "Odštevanje",
        "privateJoin": "Vstop v zasebni klepet",
        "privateRequest": "Prošnja za zasebni klepet",
        "timerGong": "Zvon za konec odštevalnika",
        "voteCast": "Oddano glasovanje",
        "voteTick": "Tiktakanje ure za glasovanje",
        "voteTickShort": "Tiktakanje ure za glasovanje (<1s)"
      },
      "tab_advanced": "Napredni",
      "tab_chat": "Klepet",
      "tab_game": "Igra",
      "tab_general": "General",
      "tab_shortcuts": "Bližnjice",
      "tab_user": "Uporabnik",
      "title": "Nastavitve aplikacije",
      "title_avatar": "Izberi Avatarja",
      "title_sound": "Glasnost zvočnih efektov"
    },
    "setup": {
      "audio_devices": "Avdio naprave",
      "audio_error": "Zvočne povezave ni mogoče vzpostaviti",
      "audio_unnamed": "Neimenovana avdio naprava",
      "browser": "Iskalnik:",
      "button_rerun": "Ponovitev",
      "button_start": "Začni",
      "cam_blocked": "Dostop do kamere je onemogočen",
      "cam_query": "Preverjanje dovoljenj za kamero",
      "capture_audio": "Snemaj avdio",
      "capture_video": "Snemaj video",
      "get_devices": "Pridobi seznam naprav",
      "mic_blocked": "Dostop do mikrofona je onemogočen",
      "mic_cam_blocked": "Omogoči dostop do kamere in mikrofona",
      "mic_cam_query": "Dostopaj do kamere in mikrofona",
      "mic_only": "Dostop samo do mikrofona",
      "mic_query": "Preverjanje dovoljenj za mikrofon",
      "no_devices": "Ni bilo najdenih ustreznih naprav",
      "self_listen": "Poslušaj se",
      "start": "Začni",
      "step": "Korak {0}:",
      "text": "Ta nastavitev bo poskusila dostopati do vaše kamere in mikrofona, ko pritisnete {0}. Če se pojavijo napake, bodo prikazane pod vsakim korakom.",
      "title": "Nastavi Mikrofon in Kamero",
      "video_devices": "Video naprave",
      "video_error": "Video povezave ni mogoče vzpostaviti",
      "video_unnamed": "Neimenovana video naprava"
    },
    "signal": {
      "bluffs": "Liki za pretvarjanje:",
      "cards": {
        "ability": "Uporabi svojo sposobnost?",
        "acknowledge": "Razumem",
        "anticlockwise": "Proti urinem kazalcu",
        "bluffs": "Ti liki niso v igri",
        "choice": "Odloči se",
        "claim": "Ta igralec je",
        "clockwise": "V smeri urinega kazalca",
        "demon": "To je Demon",
        "evil": "Zloben",
        "five": "Pet",
        "four": "Štiri",
        "good": "Dobro",
        "minions": "To so tvoji Podložniki",
        "neutral": "Nevtralno",
        "no": "Ne",
        "one": "Ena",
        "selected": "Ta lik te je izbral",
        "three": "Tri",
        "two": "Dve",
        "yes": "Ja",
        "you": "Ti si",
        "zero": "Nič"
      },
      "character": "Lik",
      "custom": "Po meri",
      "grimoire": "Čarovniška Knjiga",
      "message": "Sporočilo:",
      "player": "Igralec",
      "player_text": "Izberi igralca tako, da klikneš na njegov žeton v Čarovniški Knjigi.",
      "prompt_custom_placeholder": "Sporočilo po meri",
      "prompt_custom_player": "Kaj želiš vprašati Pripovedovalca?",
      "prompt_custom_st": "Kaj želiš povedati igralcu?",
      "prompt_custom_title": "Pošlji sporočilo po meri",
      "received": "Prejeto",
      "response": "Odgovor:",
      "saw_this": "{0} je videl to",
      "select_everyone": "Izberi vse",
      "selected_players": "Izberi igralce",
      "sent": "Poslano",
      "storyteller": "Pripovedovalec|Pripovedovalci",
      "title": "Zbudi {0}",
      "title_character": "Izberi lik",
      "title_player": "Izberi igralca",
      "title_spec": "Pripovedovalec je zbudil {0}:",
      "title_st": "Pripovedovalec te je zbudil:",
      "warning_dead": "Ta igralec je mrtev.",
      "warning_droison": "Ta igralec je pijan / zastrupljen.",
      "warning_vortox": "Sposobnosti Meščanov prinašajo lažne informacije."
    },
    "update": {
      "bugfix": "Poprava napak",
      "feature": "Nove funkcije",
      "general": "Splošne spremembe",
      "other": "Druge spremembe",
      "title": "Nove posodobitve:"
    },
    "user": {
      "button_add_st": "Dodaj Pripovedovalca",
      "button_cancel_st": "Prekliči Pripovedovalčevo prošnjo",
      "button_kick_user": "Odstrani uporabnika",
      "button_mod_user": "Uporabnik moderator",
      "button_remove_st": "Odstrani Pripovedovalca",
      "error": "Pojavila se je napaka pri nalaganju uporabnikovih podatkov.",
      "grimoire_access_grant": "Dovoli dostop do Čarovniške Knjige",
      "grimoire_access_revoke": "Onemogoči dostop do Čarovniške Knjige",
      "loading": "Nalaganje uporabnika...",
      "prompt_kick": "Res želiš odstraniti {0} iz igre?",
      "prompt_st": "Res želite, da {0} postane Pripovedovalec?\nKo potrdi prošnjo, bo prejel vse zmožnosti Pripovedovalca in dostop do Čarovniške Knjige.",
      "title": "Profil uporabnika"
    },
    "users": {
      "chat_connection": "Vrsta povezave v pogovor",
      "grim_access": "Dostop do Čarovniške Knjige",
      "group_sub": "Naročnik na skupino",
      "new_user": "Nov uporabnik",
      "official_mod": "Uradni moderator",
      "official_tpi": "Uradni TPI",
      "offline": "Brez povezave",
      "st_requested": "Pripovedovalec je prosil",
      "type_player": "Igralec|{n} Igralcev",
      "type_spectator": "Gledalec|{n} Gledalcev",
      "type_storyteller": "Pripovedovalec|{n} Pripovedovalcev"
    },
    "verification": {
      "button_reset": "Ponastavi",
      "code": "Koda",
      "code_sent": "Kodo smo poslali na tvojo telefonsko številko, prosim vpiši jo da potrdiš svoj račun!",
      "country_code": "Klicna koda države",
      "error_402": "Začasne telefonske številke ne smejo biti uporabljene za preverjanje uporabniškega računa.",
      "error_403": "Ta telefonska številka je že v uporabi. Če mislite, da je prišlo do napake, nas kontaktirajte na {0}.",
      "error_404": "Poskus potrditve ni več na voljo. Prosim poskusite še enkrat.",
      "error_assigned": "Ta telefonska številka je že v uporabi. Prosim, uporabite drugo telefonsko številko.",
      "error_cooldown": "Doseženo je bilo najvišje število poskusov. Prosim, počakajte vsaj {0} minut, preden ponovno poskusite.",
      "error_other": "Nekaj je šlo narobe: {0}. Prosim, poskusite še enkrat.",
      "error_pending": "Napačna koda. Prosim, poskusite še enkrat.",
      "error_restart": "Doseženo je bilo najvišje število poskusov. Prosim, ponovno vnesite telefonsko številko.",
      "phone": "Telefonska številka",
      "success": "Potrditev uspešna! Lahko zaprete okno.",
      "text_body": "Uveljavljamo SMS potrditev za nove uporabniške račune {0}, da lahko zaščitimo živahno, spoštljivo družbo, ki dela Kri na Zvoniku posebno. Medtem ko večina igralcev že prispeva k tej fantastični kulturi, nam ta korak pomaga pri hitrem ukrepanju, ko je vaša iskušnja z igro motena. To ne velja za zasebne igre.",
      "text_body2": "Javne igre",
      "text_footer": "Telefonske številke so shranje na nepovraten način.",
      "text_title": "Zakaj se to potrebuje?",
      "title": "Potrditev uporabniškega računa"
    },
    "votehistory": {
      "clear": "Izbriši zgodovino glasovanja",
      "execution": "Usmrtitev",
      "exile": "Izgon",
      "majority": "Večina",
      "nominator": "Nominator",
      "nominee": "Nominiranec",
      "phase": "Faza",
      "pregame": "Predigra",
      "title": "Zgodovina glasovanja",
      "type": "Tip",
      "voters": "Glasovalci",
      "votes": "Glasovi"
    }
  },
  "overlays": {
    "attention": {
      "attention": "Prosim za pozornost!",
      "return": "Prosim vrnite se na Mestni trg!"
    },
    "firstnight": {
      "bluffs": "Izberi 3 prazne \"Lik za pretvarjanje\" žetone in jih deli z Demonom.",
      "button_begin": "Začni prvo nočno fazo",
      "gardener_button": "Pošlji like",
      "gardener_text": "Ko si zadovoljen z liki, {0} svojim igralcem. Ko si jih razdelil, lahko začneš s pripravljanjem prve noči.",
      "reminders": "Dodaj katerekoli {0} žetone za opomnik.",
      "title": "Pripravi prvo noč"
    },
    "gatherplayers": {
      "button_add": "Dodaj sedež",
      "button_clear": "Izbriši prazne",
      "button_clearall": "Izbriši vse",
      "button_select": "Izberi izdajo",
      "button_shuffle": "Premešaj sedeže",
      "clear_text": "Ste prepričani, da želite odstraniti vse igralce?",
      "clear_title": "Odstrani vse igralce",
      "move": "Premakni po\n{0}",
      "shuffle_text": "Ste prepričani, da želite naključno razporediti sedeže?",
      "shuffle_title": "Naključno razporedi sedeže",
      "swap": "Zamenjaj z\n{0}",
      "text": "Dodaj, zmešaj ali odstrani igralske sedeže tukaj.",
      "text2": "Ko je dovolj sedežev za vse, {0}",
      "title": "Zberi svoje igralce",
      "warning": "Potrebuješ vsaj 7 igralcev za normalno igro v Lažigradu."
    },
    "nightaction": {
      "open-eyes": {
        "button_close": "Zapri",
        "button_open": "Odpri",
        "button_peek": "Špegaj",
        "state_false": "Zaprto",
        "state_open-eyes": "Odprto",
        "state_peek-eyes": "Špeganje",
        "text": "Tvoje oči so {0}",
        "tooltip_false": "Ne boš videl nočnih sporočil drugih igralcev in ne boš mogel pošiljati zasebnih sporočil nikomer, razen tvojima sosedoma ali Pripovedovalcu.",
        "tooltip_open-eyes": "Lahko pošiljaš in prejemaš zasebna sporočila vseh igralcev, ne glede na to kje sedijo. Videl boš vsebino vsakega nočnega signala, poslanega in prejetega, vendar obstaja možnost, da te kdo vidi.",
        "tooltip_peek-eyes": "Lahko pošiljaš in prejemaš zasebna sporočila vseh igralcev, ne glede na to, kje sedijo. Videl boš, kdo pošilja in prejema nočnege signale, ampak ne vsebine. Tega nihče ne vidi."
      }
    },
    "pointing": {
      "button_countdown": "Odštevanje",
      "countdown_freeze": "Zamrzniti",
      "nobody": "Nihče",
      "prompt": "Klikni na igralca, da pokažeš nanj!",
      "title_locked": "Izbrani igralec:|Izbrani igralci:",
      "title_open": "Trenutna izbira:|Trenutne izbire:",
      "you_pointed": "Pokazal si na:"
    },
    "reveal": {
      "button_remaining": "Ostali igralci",
      "button_result": "Rezultat igre",
      "evil": "Zlo",
      "good": "Dobro",
      "prompt": "Opozorilo: To bo končalo igro in razkrilo Čarovniško Knjigo vsem igralcem!\nKdo je zmagal igro?",
      "result": "{0} je zmagalo!",
      "text": "Razkrij rezultat igre in igralce, tako da klikneš na njihove žetone. Lahko se pomakneš z miško čez žeton, da pošpegaš kateri lik je na njem.",
      "title": "Razkrij Čarovniško Knjigo"
    },
    "rules": {
      "button_select": "Izberi Like",
      "text": "Pripravljen si na {0}",
      "text2": "Popotniki naj bodo določeni igralcem pred izbiro likov.",
      "title": "Izberi Like"
    },
    "towninfo": {
      "alive": "Živ",
      "button_gather": "Zberi Svoje Igralce",
      "return": "Vrni se k Čarovniški Knjigi (Bljižnica: {0})",
      "script_by": "za {0}",
      "text_player": "Pripovedovalec mora dodati več igralcev preden začnete.",
      "text_st": "Za začetek moraš najprej {0}",
      "timer_ended": "končano",
      "title": "Dobrodošli na {0}."
    },
    "vote": {
      "accusation": "Obtožba",
      "button_chat": "Odprti klepet",
      "button_clear_selection": "Počisti izbiro",
      "button_countdown": "Odštevanje",
      "button_defense": "Začni z Zagovorom",
      "button_hand_down": "DOL",
      "button_hand_up": "GOR",
      "button_mark": "Oznaka",
      "button_mark_remove": "Odstrani Oznako",
      "button_pause": "Pavza",
      "button_reset": "Ponastavi",
      "button_restart": "Ponovno začni",
      "button_resume": "Nadaljuj",
      "button_select_player": "Izberi igralca",
      "button_set_highscore": "Nastavi število glasov",
      "button_start": "Začni",
      "choose_defense_attorney": "Izberi zagovornika!",
      "countdown_go": "Pojdi",
      "defense": "Zagovor",
      "defense_attorney": "Zagovornik",
      "highscore_placeholder": "Največ preštetih glasov",
      "highscore_text": "Vstavi novo številko za današnjo večino pri glasovanju\n ali pusti prazno, da je večina enaka normalni večini živih igralcev.",
      "highscore_title": "Spremeni večino za glasovanje",
      "majority": "Večina je {0} glas|Večina je {0} glasov",
      "no_majority": "Večina ni potrebna",
      "pointing": "Kaže na {0}",
      "secret": "Glasovanje bo skrito.",
      "secret_vote": "Skrito glasovanje",
      "votes": "{0}glas za izenačitev, {1} za usmrtitev|{0} glasov za izenačitev, {1} za usmrtitev",
      "warning_shortcuts": "Bližnjice so izklopljene!"
    },
    "whisper": {
      "muted": "Ta igralec je utišan v glasovnem klepetu.",
      "video_muted": "Ta igralec ima ugasnjeno kamero."
    }
  },
  "pages": {
    "banned": {
      "description": "Vaš uporabniški račun je bil {0} zaradi vaših nedavnih dejanj in ga ni več mogoče uporabljati za igranje na aplikaciji.",
      "description_banned": "zaklenjen",
      "expires": "Vaš uporabniški račun je zaklenjen do:",
      "expires2": "Prosim ne ponavljajte svojih kršitev, drugače je lahko vaš uporabniški račun dokončno zakljenjen.",
      "footer1": "Če potrebujete pomoč, nas kontaktirajte na {0}.",
      "footer2": "Zapomni si:",
      "footer3": "Ubij elegantno in umri z dostojanstvom.",
      "permanent": "Vaš uporabniški račun je bil dokončno zaklenjen.",
      "reason": "Zaradi naslednjih razlogov:",
      "title": "Zaklenjen uporavniki račun"
    },
    "clock": {
      "description": "Ura na vašem računalniku je trenutno narobe za {0}. To lahko povzroči težave med spletno igro. Lahko sinhronizirate uro na vašem računalniku {1}. Ko se sinhronizira, ponovno osvežite aplikacijo.",
      "description_mins": "1 minuta|{n} minut",
      "description_online": "na spletu",
      "return": "Vrni se na Aplikacijo",
      "title": "Prosim sinhronizirajte uro na vašem računalniku"
    },
    "lobby": {
      "bootlegger_title": "Pozor!",
      "bootlegger_warning": "Ta seja ima Lorica Švercerja, kar pomeni, da ima pravila in like, ki niso uradno izdani, in je zato primera za bolj izkušene igralce.\nČe ste začetniki pri igri Kri na Zvoniku, vam priporočamo, da najprej osvojite standardna pravila in like z eno od uradnih osnovnih skript. Kuhajo se težave je najbolj primerna za prve igre!\nVsekakor dobrodošli - veseli smo da ste se nam pridružili!\nSte prepričani, da se želite pridružiti tej seji?",
      "button_create_game": "Ustvari igro",
      "button_help": "Pomoč",
      "button_join_game": "Pridruži se zasebni igri",
      "button_local_play": "Lokalna igra",
      "button_mod": "Skrbnik",
      "button_quit": "Izhod",
      "button_settings": "Nastavitve",
      "button_verify": "Potrdi uporabniški račun",
      "characters": "Liki",
      "create_game": "Ustvari novo igro",
      "edition_by": "od {author}",
      "forced_private": "Ne morete več igrati v javnih igrah.",
      "free_tier_free": "Zastonj",
      "free_tier_patreon": "Patreon",
      "free_tier_unverified": "Imate {0} uporabniški račun. Lahko igrate v katerikoli igri zgoraj s klikom na gumb na levi, razen če zanjo potrebujete naročnino. Če želite voditi svoje igre, se lahko naročite na {1}.",
      "free_tier_verified": "Imate {0} uporabniški račun. Potrebujete {1} preden lahko igrate v javnih igrah. Če želite voditi svoje igre, se lahko naročite na {2}.",
      "free_tier_verify": "potrdi svoj uporabniški račun",
      "game": "Igra",
      "language": "Jezik",
      "loading": "Nalagam igre...",
      "no_games": "Javnih iger ni bilo mogoče najti.",
      "npcs": "Neigralski Liki",
      "page": "Stran {page} od {total}",
      "phase": "Faza",
      "players": "Igralci",
      "script": "Skripta",
      "show_private": "Prikaži zasebne igre",
      "spectators": "Gledalci",
      "stats": "{0} uporabnikov je v {1}{2} igrah",
      "stats_public": "javno",
      "storyteller": "Pripovedovalec",
      "subscription": "Nivo naročnine",
      "updating": "Posodablam...",
      "welcome": "Dobrodošli v {0}!"
    },
    "login": {
      "description": "Prosim vpišite se ali ustvarite uporabniški račun za nadaljevanje:",
      "email": "Elektronski naslov",
      "error_captcha": "Prosim naredite captcho",
      "error_password": "Gesli se ne ujemata",
      "login": "Vpis",
      "password": "Geslo",
      "password_confirm": "Potrditev gesla",
      "password_reset": "Navodila za ponastavitev gesla so bila poslana na vaš elektronski naslov.",
      "recover_password": "Obnovi Geslo",
      "register": "Registriraj se",
      "subscribe": "Naroči se na e-poštni seznam",
      "title": "Dobrodošli na Kri na Zvoniku Online - V delu!",
      "username": "Uporabniško ime"
    },
    "update": {
      "description": "Trenutno uporabljate verzijo {0}, najnovejša verzija je {1}.",
      "download": "Prenesi najnovejšo {label} verzijo tukaj.",
      "reload": "Prosim osvežite stran ali počistite predpomnilnik brskalnika za posodobitev.",
      "title": "Prosim posodobite vašo aplikacijo"
    },
    "verification": {
      "button_resend": "Ponovno pošlji kodo",
      "code": "6-mestna koda",
      "description": "Prosim potrdite vaš uporabniški račun za nadaljevanje. Poslali smo kodo na vaš elektronski naslov - vnesite jo za nadaljevanje. Ne morate dostopati do elektronskega naslova?",
      "email_success": "E-pošta uspešno poslana.",
      "error_429": "Prosim počakajte vsaj {0} sekund preden poskusite še enkrat.",
      "error_disposable": "Enkratnega elektronskega naslova ne morete uporabiti za potrditev uporabniškega računa.",
      "error_verified": "Že potrjeno",
      "error_wrong": "Napačna koda, prosim poskusite še enkrat.",
      "link": "Lahko spremenite tukaj."
    }
  },
  "player": {
    "menu": {
      "alignment": "Spremeni Razvrstitev",
      "character": "Spremeni Lik",
      "chat": "Prosi za Zasebni Klepet",
      "empty": "Prazen Stol",
      "empty_text": "Res želite odstraniti igralca z njegovega stola med igro?",
      "empty_title": "Prazen stol od {0}",
      "follow": "Sledi Igralcu",
      "nominate": "Nominiraj sebe",
      "unfollow": "Prenehaj slediti Igralcu",
      "wake": "Zbudi",
      "whisper": "Pošlji Besedno Sporočilo"
    },
    "name": {
      "claim": "Klikni za sedenje",
      "connecting": "Ta igralec se povezuje v glasovni klepet.",
      "follow": "Slediš temu igralcu.",
      "listening": "Ta igralec posluša glasovni klepet.",
      "move": "Premakni tega igralca.",
      "offline": "Ta igralec trenutno ni na voljo.",
      "remove": "Odstrani tega igralca.",
      "remove_text": "Res želite odstraniti Stol {0}?\nTrenutno na njem sedi {1}.",
      "remove_title": "Odstrani Stol",
      "seat_text": "(to bo vidno samo tebi)",
      "seat_title": "Spremeni ime Stola"
    },
    "overlay": {
      "eyes_open": "Ima odprte oči",
      "night_info_received": "Nočne informacije prejete",
      "night_info_sent": "Nočne informacije poslane",
      "nominate": "Nominiraj tega igralca",
      "point": "Pokaži na tega igralca",
      "select": "Izberi tega igralca"
    },
    "reminders": {
      "add": "Dodaj Opomnik",
      "edit": "Uredi Opomnik {0}",
      "edit_placeholder": "Beležka po meri",
      "edit_text": "Uredi beležko po meri za {0}",
      "edit_title": "Uredi Opomnik",
      "flip": "Obrni Opomnik {0}",
      "remove": "Odstrani Opomnik {0}",
      "saved_favorite": "Shranjeno med priljubljene"
    },
    "shroud_add": "Igralci ne vidijo tega mrtvaškega prta. Podnevi klikni še enkrat, da postane viden.",
    "shroud_remove": "Igralci vidijo ta mrtvaški prt. Podnevi klikni še enkrat, da postane neviden.",
    "toggle_status": "Spremeni stanje"
  },
  "session": {
    "access": "Dostop",
    "copy": "Klikni za kopiranje",
    "created": "Ustvaril {1} pred {0}.",
    "free": "Zastonj za vse",
    "language": "Jezik klepeta",
    "locked": "Pripovedovalci in Igralci",
    "locked_text": "Samo igralci, ki sedijo, in trenutni Pripovedovalci se lahko pridružijo tej seji.",
    "name_placeholder": "Ime seje",
    "open_text": "Vsi se lahko pridružijo tej seji.",
    "prompt_public_text": "Ste prepričani, da želite narediti to sejo vidno javnosti?\nTo bo dovolilo vsem, da gledajo igro in se ji pridružijo.",
    "prompt_public_title": "Naredi sejo javno",
    "server": "Strežnik za Klepet:",
    "server_name": "Ime",
    "server_stats": "{0} uporabnikov, {1} obremenitev strežnika",
    "session_name": "Ime seje",
    "subscription_needed": "Potrebna je naročnina",
    "tags": "Oznake za Javno Igro",
    "title_create": "Ustvari sejo igre",
    "title_current": "Trenutna seja igre",
    "visibility": "Vidnost",
    "visibility_private": "Zasebno",
    "visibility_public": "Javno"
  },
  "storyteller": {
    "connecting": "Pripovedovalec se povezuje v glasovni klepet.",
    "follow": "Sledi Pripovedovalcu",
    "following": "Slediš temu Pripovedovalcu.",
    "listening": "Pripovedovalec posluša glasovni klepet.",
    "offline": "Pripovedovalec trenutno ni na voljo.",
    "prompt_grim_text": "Novi uporabniki ne morejo prositi za dostop do Čarovniške Knjige v javnih igrah.\nProsim odigrajte več igre za odklep te funkcije.",
    "prompt_grim_title": "Napaka pri prošnji za dostop do Čarovniške Knjige",
    "remove": "Odstrani Pripovedovalca",
    "request_grim": "Prosi za dostop do Čarovniške Knjige",
    "title": "Pripovedovalci",
    "unfollow": "Prenehaj slediti Pripovedovalcu"
  },
  "tabs": {
    "bluffs": {
      "title": "Blefi"
    },
    "character": {
      "download": "Prenesi JSON skripte",
      "error_popout": "Napaka pri ustvarjanju okna",
      "error_save": "Napaka pri shranjevanju datoteke",
      "jinxes": "Posebni učinki",
      "other_nights": "Ne\nprvo noč",
      "popout": "Izvrzi zavihek z liki",
      "popout_window": "Odpri zavihek z liki v novem oknu"
    },
    "characters": {
      "title": "Liki"
    },
    "chat": {
      "accept": "Sprejmi prošnjo",
      "accept_request": "Sprejmi prošnjo za klepet z {0}",
      "cancel": "Zavrni prošnjo",
      "cancel_request": "Zavrni prošnjo za klepet z {0}",
      "channels": {
        "bmr_0": "Krčma",
        "bmr_1": "Koča",
        "bmr_2": "Močvirje",
        "bmr_3": "Kmetija",
        "bmr_4": "Prikolica",
        "custom_0": "Trgovina z napoji",
        "custom_1": "Stolp",
        "custom_2": "Katedrala",
        "custom_3": "Taborni ogenj",
        "custom_4": "Pobrežje",
        "snv_0": "Zeliščni vrt",
        "snv_1": "Rastlinjak",
        "snv_2": "Jame",
        "snv_3": "Tempelj",
        "snv_4": "Cirkuški šotor",
        "tb_0": "Samostan",
        "tb_1": "Cerkev",
        "tb_2": "Pokopališče",
        "tb_3": "Knjižnica",
        "tb_4": "Laboratorij"
      },
      "chats": "Klepeti",
      "following": "Slediš temu igralcu.",
      "incoming": "Prihajajoč",
      "leave_private": "Zapusti zasebni klepet",
      "leave_room": "Zapusti sobo",
      "night": "Padla je noč...",
      "nomination": "Igralec je bil nominiran!",
      "outgoing": "Odhajajoč",
      "request_private": "Zaprosi za zasebni klepet",
      "requests": "Prošnje za klepet",
      "reset_position": "Ponastavi položaj",
      "spectator": "Gledalec",
      "title": "Glas"
    },
    "night": {
      "popout": "Izvrzi nočni red",
      "toggle": "Vklopi/izklopi nočni red"
    },
    "npcs": {
      "remove_fabled": "Odstrani Pravljične",
      "remove_loric": "Odstrani Loric",
      "title": "NPC-ji"
    },
    "text": {
      "channels": {
        "private": "Zasebno",
        "public": "Javno",
        "spectator": "Gledalci",
        "system": "Seja"
      },
      "message_blocked": "ni dostavljeno",
      "message_to": "na",
      "prompt_private": "Zasebni klepet",
      "prompt_public": "Javno obvestilo",
      "prompt_spectator": "Klepet za gledalce",
      "prompt_system": "Sistemsko sporočilo",
      "prompt_user": "Za {0}",
      "system": {
        "death": "{0} je umrl.",
        "end_evil": "Igre je konec in Zlobna ekipa je zmagala!",
        "end_good": "Igre je konec in Dobra ekipa je zmagala!",
        "grim_deny": "{0} je dobil zavrnjen dostop do Čarovniške Knjige.",
        "grim_receive": "{0} je dobil dostop do Čarovniške Knjige.",
        "grim_remove": "{0} nima več dostopa do Čarovniške Knjige.",
        "grim_request": "{0} je prosil za dostop do Čarovniške Knjige.",
        "join": "{0} se je pridružil igri.",
        "leave": "{0} je zapustil igro.",
        "phase": "{0} se je začel.",
        "revive": "{0} je bil oživljen.",
        "seat_claim": "{0} se je vsedel na stol {1}.",
        "seat_empty": "{0} je bil odstranjen s stola {1}.",
        "seat_vacate": "{0} je odšel s stola {1}.",
        "signal": "{0} je poslal nočni signal {1}.",
        "start": "Igra se je začela in liki so razdeljeni!",
        "storyteller_add": "{0} je postal Pripovedovalec.",
        "storyteller_remove": "{0} je prenehal biti Pripovedovalec.",
        "vote": "{0} je uporabil svoj Duhovni Glas."
      },
      "title": "Besedilo",
      "tooltip": "Prikaži {0} neprebranih sporočil z {1}"
    }
  },
  "user": {
    "avatar_enabled": "Avatar viden",
    "camera_enabled": "Kamera vidna",
    "error_avatar_text": "Izbrani avatar je velikosti {0}MB, največja dovoljena velikost je {1}MB.",
    "error_avatar_title": "Prevelika datoteka",
    "gain": "Pridobitev",
    "group_subscription": "Skupinska naročnina",
    "id": "ID uporabnika",
    "level": "Nivo uporabniškega računa",
    "mic_volume": "Glasnost Mikrofona",
    "new_user": "Nov Uporabnik",
    "pronouns": "zaimki",
    "registration": "Registracija",
    "statistics": "Statistika",
    "stats": {
      "edition": "Najbolj igrane\nIzdaje",
      "homebrew": "Doma zvarjen Lik",
      "loading": "Nalagam statistiko...",
      "none": "Nihče",
      "player": "Igre\nOdigrane",
      "player_wins": "{0}% Možnost zmage",
      "role": "Najboljši Začetni\nLiki",
      "st_evil_wins": "{0}% Možnost zmage Zla",
      "storyteller": "Igre\nPripovedovane",
      "warning": "Statistika se nalaga...\nPonovno preveri kasneje!"
    },
    "stats_hidden": "Skrit",
    "stats_private": "Zasebno",
    "stats_public": "Javno",
    "upload_avatar": "Naloži Avatarja",
    "verified": "Preverjen Uporabnik"
  },
  "version": {
    "character_distribution": "Porazdelitev likov",
    "download": "Prosim prenesite in naložite najnovejšo {0} verzijo tukaj.",
    "players_alive": "{0}/{1} igralcev je živih",
    "reload": "Prosim ponovno naložite ali počistite predpomnilnik brskalnika za pridobitev najnovejše verzije.",
    "since": "od {0}",
    "translation_disclaimer": "Trenutno uporabljate lokalno verzijo aplikacije. Ta prevod so ustvarili in pregledali naslednji prostovoljci, ki niso del organizacije The Pandemonium Institute:",
    "translation_game": "Ta prevod morda ni točno skladen z uradnimi angleškimi pravili igre, ki jih je napisal The Pandemonium Institute.",
    "travellers_alive": "{0} / {1} Popotnikov je živih",
    "update": "Prosim posodobi!",
    "updating": "Posodabljam aplikacijo na verzijo {0}...",
    "warning_browser": "Uporabljaš star ali nepodprt brskalnik",
    "warning_browser2": "{0} lahko povzroči težave z aplikacijo. Prosim prenesite najnovejše posodobitve brskalnika ali zamenjajte brskalnik. Ta aplikacija najbolje deluje na brskalnikih Firefox in Chrome.",
    "warning_update": "Tvoja verzija aplikacije je zastarela",
    "warning_update2": "{0} najnovejša verzija je {1}!"
  }
}
